pypaca/__init__.py
pypaca/profiler.py
pypaca/time.py
pypaca-0.0.2.dist-info/LICENSE
pypaca-0.0.2.dist-info/METADATA
pypaca-0.0.2.dist-info/WHEEL
pypaca-0.0.2.dist-info/top_level.txt
pypaca-0.0.2.dist-info/RECORD
